spacectl/__init__.py
spacectl/main.py
spacectl/command/__init__.py
spacectl/command/api_resource.py
spacectl/command/apply.py
spacectl/command/config.py
spacectl/command/execute.py
spacectl/command/template.py
spacectl/command/version.py
spacectl/conf/__init__.py
spacectl/conf/global_conf.py
spacectl/conf/my_conf.py
spacectl/lib/__init__.py
spacectl/lib/output.py
spacectl/lib/template.py
spacectl/lib/apply/__init__.py
spacectl/lib/apply/store.py
spacectl/lib/apply/task.py
spacectl/lib/apply/task_manager.py
spacectl/lib/parser/__init__.py
spacectl/lib/parser/default.py
spacectl/modules/__init__.py
spacectl/modules/concat.py
spacectl/modules/csv.py
spacectl/modules/date.py
spacectl/modules/export_excel.py
spacectl/modules/export_google_sheets.py
spacectl/modules/export_mysql.py
spacectl/modules/export_s3.py
spacectl/modules/join.py
spacectl/modules/print.py
spacectl/modules/shell.py
spacectl/modules/resource/__init__.py
spacectl/modules/resource/validate.py
spacectl-2.0.10.dist-info/METADATA
spacectl-2.0.10.dist-info/WHEEL
spacectl-2.0.10.dist-info/entry_points.txt
spacectl-2.0.10.dist-info/top_level.txt
spacectl-2.0.10.dist-info/RECORD
