Metadata-Version: 2.1
Name: spacectl
Version: 2.0.10
Summary: SpaceONE Command Line Interface
Home-page: https://www.spaceone.dev/
Author: MEGAZONE SpaceONE Team
Author-email: admin@spaceone.dev
License: Apache License 2.0
Platform: UNKNOWN
Requires-Dist: spaceone-core
Requires-Dist: tabulate
Requires-Dist: jinja2
Requires-Dist: pandas
Requires-Dist: google-api-core
Requires-Dist: google-api-python-client
Requires-Dist: gspread
Requires-Dist: oauth2client
Requires-Dist: boto3
Requires-Dist: PyMySQL
Requires-Dist: openpyxl
